lowbudget2gocli.py
lowbudget2gocli-0.1.0.dist-info/entry_points.txt
lowbudget2gocli-0.1.0.dist-info/WHEEL
lowbudget2gocli-0.1.0.dist-info/METADATA
lowbudget2gocli-0.1.0.dist-info/RECORD
