Metadata-Version: 2.1
Name: lowbudget2gocli
Version: 0.1.0
Summary: A console program that allows developers to rea gossips, post gossips, comment and like gossips
Author: adeayo-py
Requires-Python: >=3.7,<4.0
Classifier: Programming Language :: Python :: 3
Classifier: Programming Language :: Python :: 3.7
Classifier: Programming Language :: Python :: 3.8
